{"_ts":[1504247146,1504290946,1504335004,1504378488,1504422596],"_r":{"breakdown":{"html":{"bytes":[171580,171566,158172,158174,171375],"requests":[6,6,6,6,6]},"js":{"bytes":[463285,462988,463496,462929,488932],"requests":[33,33,33,33,33]},"css":{"bytes":[21189,21235,21235,21235,21235],"requests":[2,2,2,2,2]},"image":{"bytes":[5783415,5783518,5783331,5783587,5783569],"requests":[58,58,58,58,58]},"flash":{"bytes":[0,0,0,0,0],"requests":[0,0,0,0,0]},"font":{"bytes":[80865,80865,80865,80865,80865],"requests":[5,5,5,5,5]},"other":{"bytes":[2972,2970,2972,2970,2972],"requests":[3,3,3,3,3]}},"date":[1504247146,1504290946,1504335004,1504378488,1504422596],"domElements":[1992,1992,1911,1911,1992],"domInteractive":[2525,2244,2462,2168,1959],"firstPaint":[2009,1990,1868,1849,1707],"fullyLoaded":[15555,16054,15254,15609,17665],"id":["170901_XH_f1937838a6dbce07ecef54dc9a3b5454","170901_N8_b46440b67ee42c50eb0de8be07eadf3b","170902_5M_6ec06a31540c7266437b9835b3226cd0","170902_G1_43de79e82fe725a5ec92c3b84758a033","170903_9Y_7bb6ea14422d4938cc504a21af9d9202"],"loadTime":[5814,6206,5488,5839,7940],"render":[2465,2699,2273,2593,2292],"SpeedIndex":[2831,3855,2646,3768,3249],"TTFB":[671,509,642,596,609],"videoFrames":[[{"_i":"frame_0000.jpg","_t":0,"_vc":0},{"_i":"frame_0025.jpg","_t":2500,"_vc":48},{"_i":"frame_0027.jpg","_t":2700,"_vc":91},{"_i":"frame_0045.jpg","_t":4500,"_vc":93},{"_i":"frame_0050.jpg","_t":5000,"_vc":97},{"_i":"frame_0052.jpg","_t":5200,"_vc":98},{"_i":"frame_0064.jpg","_t":6400,"_vc":100}],[{"_i":"frame_0000.jpg","_t":0,"_vc":0},{"_i":"frame_0027.jpg","_t":2700,"_vc":48},{"_i":"frame_0048.jpg","_t":4800,"_vc":92},{"_i":"frame_0049.jpg","_t":4900,"_vc":93},{"_i":"frame_0054.jpg","_t":5400,"_vc":98},{"_i":"frame_0055.jpg","_t":5500,"_vc":98},{"_i":"frame_0064.jpg","_t":6400,"_vc":100}],[{"_i":"frame_0000.jpg","_t":0,"_vc":0},{"_i":"frame_0023.jpg","_t":2300,"_vc":52},{"_i":"frame_0027.jpg","_t":2700,"_vc":92},{"_i":"frame_0043.jpg","_t":4300,"_vc":94},{"_i":"frame_0047.jpg","_t":4700,"_vc":98},{"_i":"frame_0048.jpg","_t":4800,"_vc":100}],[{"_i":"frame_0000.jpg","_t":0,"_vc":0},{"_i":"frame_0026.jpg","_t":2600,"_vc":49},{"_i":"frame_0048.jpg","_t":4800,"_vc":92},{"_i":"frame_0051.jpg","_t":5100,"_vc":98},{"_i":"frame_0053.jpg","_t":5300,"_vc":98},{"_i":"frame_0061.jpg","_t":6100,"_vc":98},{"_i":"frame_0062.jpg","_t":6200,"_vc":100}],[{"_i":"frame_0000.jpg","_t":0,"_vc":0},{"_i":"frame_0023.jpg","_t":2300,"_vc":48},{"_i":"frame_0039.jpg","_t":3900,"_vc":92},{"_i":"frame_0044.jpg","_t":4400,"_vc":93},{"_i":"frame_0051.jpg","_t":5100,"_vc":98},{"_i":"frame_0065.jpg","_t":6500,"_vc":100}]],"visualComplete":[6400,6400,4800,6200,6500],"lighthouse":[null,null,null,null,null],"pagespeed":[9,10,10,8,9]}}