{"_ts":[1494110235,1494111129,1494123924,1494698358,1494699357,1494752241,1494821006,1494827669,1494910352,1494913604,1495334126,1495337139,1495354604],"_r":{"breakdown":{"html":{"bytes":[0,0,0,0,0,0,0,0,0,0,0,0,0],"requests":[0,0,0,0,0,0,0,0,0,0,0,0,0]},"js":{"bytes":[0,0,0,0,0,0,0,0,0,0,0,0,0],"requests":[0,0,0,0,0,0,0,0,0,0,0,0,0]},"css":{"bytes":[0,0,0,0,0,0,0,0,0,0,0,0,0],"requests":[0,0,0,0,0,0,0,0,0,0,0,0,0]},"image":{"bytes":[0,0,0,0,0,0,0,0,0,0,0,0,0],"requests":[0,0,0,0,0,0,0,0,0,0,0,0,0]},"flash":{"bytes":[0,0,0,0,0,0,0,0,0,0,0,0,0],"requests":[0,0,0,0,0,0,0,0,0,0,0,0,0]},"font":{"bytes":[0,0,0,0,0,0,0,0,0,0,0,0,0],"requests":[0,0,0,0,0,0,0,0,0,0,0,0,0]},"other":{"bytes":[0,0,0,0,0,0,0,0,0,0,0,0,0],"requests":[0,0,0,0,0,0,0,0,0,0,0,0,0]}},"date":[1494110235,1494111129,1494123924,1494698358,1494699357,1494752241,1494821006,1494827669,1494910352,1494913604,1495334126,1495337139,1495354604],"domElements":[null,null,null,null,null,null,null,null,null,null,null,null,null],"domInteractive":[null,null,null,null,null,null,null,null,null,null,null,null,null],"firstPaint":[null,null,null,null,null,null,null,null,null,null,null,null,null],"fullyLoaded":[null,null,null,null,null,null,null,null,null,null,null,null,null],"id":["170506_KB_3SZ","170506_DW_N5F","170507_RZ_42H","170513_VY_6MX","170513_6N_R6Y","170514_Q8_6Q0","170514_WG_QGG","170515_YG_95W","170515_14_14J8","170516_58_9SW","170520_Z1_BTP","170520_CB_XVJ","170521_4R_C3P"],"loadTime":[null,null,null,null,null,null,null,null,null,null,null,null,null],"render":[null,null,null,null,null,null,null,null,null,null,null,null,null],"SpeedIndex":[null,null,null,null,null,null,null,null,null,null,null,null,null],"TTFB":[null,null,null,null,null,null,null,null,null,null,null,null,null],"videoFrames":[[{"_i":"ms_000000.jpg","_t":0,"_vc":100}],[{"_i":"ms_000000.jpg","_t":0,"_vc":100}],[{"_i":"ms_000000.jpg","_t":0,"_vc":100}],[{"_i":"ms_000000.jpg","_t":0,"_vc":100}],[{"_i":"ms_000000.jpg","_t":0,"_vc":100}],[{"_i":"ms_000000.jpg","_t":0,"_vc":100}],[{"_i":"ms_000000.jpg","_t":0,"_vc":100}],[{"_i":"ms_000000.jpg","_t":0,"_vc":100}],[{"_i":"ms_000000.jpg","_t":0,"_vc":100}],[{"_i":"ms_000000.jpg","_t":0,"_vc":100}],[{"_i":"ms_000000.jpg","_t":0,"_vc":100}],[{"_i":"ms_000000.jpg","_t":0,"_vc":100}],[{"_i":"ms_000000.jpg","_t":0,"_vc":100}]],"visualComplete":[null,null,null,null,null,null,null,null,null,null,null,null,null],"lighthouse":[null,null,null,null,null,null,null,null,null,null,null,null,null],"pagespeed":[79,79,68,79,68,69,79,78,68,68,68,68,68]}}