{"_ts":[1498907308,1498995042],"_r":{"breakdown":{"html":{"bytes":[135226,135126],"requests":[7,7]},"js":{"bytes":[399546,399543],"requests":[33,33]},"css":{"bytes":[12976,12976],"requests":[2,2]},"image":{"bytes":[561594,561511],"requests":[26,26]},"flash":{"bytes":[0,0],"requests":[0,0]},"font":{"bytes":[80842,80842],"requests":[5,5]},"other":{"bytes":[3228,3253],"requests":[4,4]}},"date":[1498907308,1498995042],"domElements":[643,643],"domInteractive":[2480,2236],"firstPaint":[2147,1809],"fullyLoaded":[8529,7777],"id":["170701_Z8_HQE","170702_00_HKP"],"loadTime":[5271,3793],"render":[2790,2255],"SpeedIndex":[4599,3166],"TTFB":[605,583],"videoFrames":[[{"_i":"frame_0000.jpg","_t":0,"_vc":0},{"_i":"frame_0028.jpg","_t":2800,"_vc":2},{"_i":"frame_0038.jpg","_t":3800,"_vc":25},{"_i":"frame_0046.jpg","_t":4600,"_vc":95},{"_i":"frame_0049.jpg","_t":4900,"_vc":95},{"_i":"frame_0073.jpg","_t":7300,"_vc":95},{"_i":"frame_0085.jpg","_t":8500,"_vc":95},{"_i":"frame_0087.jpg","_t":8700,"_vc":94},{"_i":"frame_0088.jpg","_t":8800,"_vc":94},{"_i":"frame_0089.jpg","_t":8900,"_vc":99},{"_i":"frame_0091.jpg","_t":9100,"_vc":100}],[{"_i":"frame_0000.jpg","_t":0,"_vc":0},{"_i":"frame_0023.jpg","_t":2300,"_vc":2},{"_i":"frame_0029.jpg","_t":2900,"_vc":25},{"_i":"frame_0032.jpg","_t":3200,"_vc":83},{"_i":"frame_0034.jpg","_t":3400,"_vc":99},{"_i":"frame_0035.jpg","_t":3500,"_vc":99},{"_i":"frame_0037.jpg","_t":3700,"_vc":99},{"_i":"frame_0053.jpg","_t":5300,"_vc":100}]],"visualComplete":[9100,5300],"lighthouse":[null,null],"pagespeed":[77,77]}}